InspiroQuotes/__init__.py
InspiroQuotes/__main__.py
InspiroQuotes-1.0.2.dist-info/METADATA
InspiroQuotes-1.0.2.dist-info/WHEEL
InspiroQuotes-1.0.2.dist-info/top_level.txt
InspiroQuotes-1.0.2.dist-info/RECORD
